[
  {
      "title"            : "User",
      "priceIsVolatile"  : true,
      "tags"             : ["user"],
      "subscriptionType" : "mo",
      "feeInterval"      : 1,
      "feeUnit"          : "months",
      "group"            : "koding",
      "description"      : "User",
      "feeAmount"        : 500
  },
  {
      "title"            : "Group",
      "priceIsVolatile"  : true,
      "tags"             : ["group"],
      "subscriptionType" : "mo",
      "feeInterval"      : 1,
      "feeUnit"          : "months",
      "group"            : "koding",
      "description"      : "Group",
      "feeAmount"        : 500
  },
  {
      "title"            : "VM",
      "priceIsVolatile"  : false,
      "tags"             : ["vm","maxvm"],
      "soldAlone"        : true,
      "subscriptionType" : "mo",
      "feeInterval"      : 1,
      "feeUnit"          : "months",
      "group"            : "koding",
      "description"      : "maxvm",
      "feeAmount"        : 500
  },
  {
      "title"            : "Always On",
      "priceIsVolatile"  : false,
      "tags"             : ["vm", "alwayson"],
      "subscriptionType" : "mo",
      "feeInterval"      : 1,
      "feeUnit"          : "months",
      "group"            : "koding",
      "description"      : "Always On",
      "feeAmount"        : 500,
      "soldAlone"        : true
  }
]
