{
  "providing": {
  },
  "name": "golang",
  "replacing": {
  },
  "license": "All rights reserved",
  "groupings": {
  },
  "long_description": "Description\n===========\n\nRequirements\n============\n\nAttributes\n==========\n\nUsage\n=====\n\n",
  "attributes": {
  },
  "description": "Installs/Configures golang",
  "version": "0.1.0",
  "maintainer": "Aleksey Mykhailov",
  "recommendations": {
  },
  "dependencies": {
  },
  "platforms": {
  },
  "suggestions": {
  },
  "maintainer_email": "aleksey@koding.com",
  "recipes": {
  },
  "conflicting": {
  }
}